rest_framework_queryset/__init__.py
rest_framework_queryset/pagination.py
rest_framework_queryset/queryset.py
rest_framework_queryset/views.py
django_rest_framework_queryset-0.3.4.dist-info/LICENSE
django_rest_framework_queryset-0.3.4.dist-info/METADATA
django_rest_framework_queryset-0.3.4.dist-info/WHEEL
django_rest_framework_queryset-0.3.4.dist-info/top_level.txt
django_rest_framework_queryset-0.3.4.dist-info/RECORD
