Metadata-Version: 2.1
Name: django-rest-framework-queryset
Version: 0.3.4
Summary: Mimicking the Django ORM queryset over rest framework api
Home-page: UNKNOWN
Author: James Lin
Author-email: james@lin.net.nz
License: MIT
Platform: UNKNOWN
Classifier: License :: OSI Approved :: MIT License
Classifier: Intended Audience :: Developers
Classifier: Programming Language :: Python
Classifier: Programming Language :: Python :: 2.7
Classifier: Programming Language :: Python :: 3.6
Classifier: Framework :: Django
License-File: LICENSE
Requires-Dist: requests (>=2.1)
